Metadata-Version: 2.1
Name: Qflash-jwt
Version: 0.0.1
Summary: a small package for implement jwt security in API
Home-page: https://github.com/Quasar-Flash
Author: Marlon Martins
Author-email: marlon.martins@qflash.com.br
License: MIT License
Keywords: Package
Platform: UNKNOWN
License-File: LICENSE
